{
  "title": "Tahajjud Prayer",
  "sections": [
    {
      "type": "section_title",
      "text": "Encouragement"
    },
    {
      "type": "paragraph",
      "text": "Praying at night, especially after one has slept for a while, is strongly encouraged in the Qur’an for the believers, and it was ordered for the Prophet (ﷺ).",
      "formatted_text": [
        {
          "type": "english_text",
          "text": "Praying at night, especially after one has slept for a while, is strongly encouraged in the Qur’an for the believers, and it was ordered for the Prophet ("
        },
        {
          "type": "arabic_text",
          "text": "ﷺ",
          "font": "Noto Kufi Arabic"
        },
        {
          "type": "english_text",
          "text": ")."
        }
      ]
    },
    {
      "type": "section_title",
      "text": "Qur’anic Basis"
    },
    {
      "type": "paragraph",
      "text": "﴿وَمِنَ اللَّيْلِ فَتَهَجَّدْ بِهِ نَافِلَةً لَّكَ عَسَىٰ أَن يَبْعَثَكَ رَبُّكَ مَقَامًا مَّحْمُودًا﴾ Surah 17:79",
      "formatted_text": [
        {
          "type": "quran_verse",
          "text": "وَمِنَ اللَّيْلِ فَتَهَجَّدْ بِهِ نَافِلَةً لَّكَ عَسَىٰ أَن يَبْعَثَكَ رَبُّكَ مَقَامًا مَّحْمُودًا",
          "font": "Amiri Quran"
        },
        {
          "type": "english_text",
          "text": "Surah 17:79"
        }
      ]
    },
    {
      "type": "section_title",
      "text": "Divine Nearness"
    },
    {
      "type": "paragraph",
      "text": "Allah (subhanahu wa-ta‘ala) is especially close to His servants during the last part of the night, and du‘a’ is even more likely to be answered at that time."
    },
    {
      "type": "section_title",
      "text": "Number of Rak‘ahs"
    },
    {
      "type": "paragraph",
      "text": "No specific number of rak‘ahs is prescribed, but the Prophet (ﷺ) used to pray eleven or thirteen lengthy rak‘ahs. Witr is included as part of the tahajjud prayer.",
      "formatted_text": [
        {
          "type": "english_text",
          "text": "No specific number of rak‘ahs is prescribed, but the Prophet ("
        },
        {
          "type": "arabic_text",
          "text": "ﷺ",
          "font": "Noto Kufi Arabic"
        },
        {
          "type": "english_text",
          "text": ") used to pray eleven or thirteen lengthy rak‘ahs. Witr is included as part of the tahajjud prayer."
        }
      ]
    },
    {
      "type": "section_title",
      "text": "Tarāwīh"
    },
    {
      "type": "paragraph",
      "text": "Tarawih prayers are those prayed at night in congregation or individually during the month of Ramadan."
    }
  ]
}